{
  "generated_at": "2026-03-25T17:23:13.600393",
  "today": "2026-03-25",
  "days": 7,
  "persona": "brian",
  "events": [
    {
      "source": "do617:food-drink",
      "name": "Discovering Georgia: Ancient Winemaking from the Cradle of Civilization",
      "description": "",
      "url": "https://do617.com/events/2026/3/26/discovering-georgia-ancient-winemaking-from-the-cradle-of-civilization-tickets",
      "start": "2026-03-26T18:00",
      "venue": "Wild Child",
      "address": "",
      "score": 8,
      "reason": "Upscale wine tasting event focused on Georgian winemaking - fits premium drink/education interest",
      "_proximity": 3
    },
    {
      "source": "do617:food-drink",
      "name": "Spring Wine Preview",
      "description": "",
      "url": "https://do617.com/events/2026/3/28/spring-wine-preview-tickets",
      "start": "2026-03-28T19:15",
      "venue": "Formaggio Kitchen",
      "address": "",
      "score": 8,
      "reason": "Spring wine preview - upscale wine tasting event",
      "_proximity": 3
    },
    {
      "source": "do617:film-theatre-performing-arts",
      "name": "Strategy, Messaging, and Power: A Conversation with Anita Dunn",
      "description": "",
      "url": "https://do617.com/events/2026/3/26/strategy-messaging-and-power-a-conversation-with-anita-dunn-tickets",
      "start": "2026-03-26T12:00",
      "venue": "John F. Kennedy Jr. Forum at the Institute of Politics",
      "address": "",
      "score": 8,
      "reason": "High-status political/messaging panel with Anita Dunn, influential strategist\u2014directly relevant to government, media, and public affairs expertise",
      "_proximity": 3
    },
    {
      "source": "do617:film-theatre-performing-arts",
      "name": "Public Service and Global Security: A Conversation with Curtis Ried",
      "description": "",
      "url": "https://do617.com/events/2026/3/31/public-service-and-global-security-a-conversation-with-curtis-ried-tickets",
      "start": "2026-03-31T12:00",
      "venue": "John F. Kennedy Jr. Forum at the Institute of Politics",
      "address": "",
      "score": 8,
      "reason": "Public Service and Global Security conversation \u2014 directly aligns with civic accountability and government policy expertise",
      "_proximity": 3
    },
    {
      "source": "do617:concerts",
      "name": "Boston Speakers Series\u2013Malcolm Gladwell",
      "description": "",
      "url": "https://do617.com/events/2026/3/25/boston-speakers-series-malcolm-gladwell-tickets",
      "start": "2026-03-25T20:00",
      "venue": "Boston Symphony Hall",
      "address": "",
      "score": 8,
      "reason": "Boston Speakers Series with Malcolm Gladwell; high-profile thought leader event",
      "_proximity": 3
    },
    {
      "source": "do617:concerts",
      "name": "Dvo\u0159\u00e1k Symphony No. 9 and Excerpts from Nixon in China with Ren\u00e9e Fleming",
      "description": "",
      "url": "https://do617.com/events/2026/3/26/dvorak-symphony-no-9-and-excerpts-from-nixon-in-china-with-renee-fleming-tickets-d0zzzpe",
      "start": "2026-03-26T19:30",
      "venue": "Symphony Hall, Boston, MA",
      "address": "",
      "score": 8,
      "reason": "Symphony performance with world-class soprano Ren\u00e9e Fleming; high-status cultural event",
      "_proximity": 3
    },
    {
      "source": "do617:concerts",
      "name": "Dvo\u0159\u00e1k Symphony No. 9 and Excerpts from Nixon in China with Ren\u00e9e Fleming",
      "description": "",
      "url": "https://do617.com/events/2026/3/26/dvorak-symphony-no-9-and-excerpts-from-nixon-in-china-with-renee-fleming-tickets",
      "start": "2026-03-26T19:30",
      "venue": "Boston Symphony Hall",
      "address": "",
      "score": 8,
      "reason": "Symphony performance with world-class soprano Ren\u00e9e Fleming; high-status cultural event",
      "_proximity": 3
    },
    {
      "source": "do617:concerts",
      "name": "Lady Gaga",
      "description": "",
      "url": "https://do617.com/events/2026/3/29/lady-gaga-tickets",
      "start": "2026-03-29T20:00",
      "venue": "TD Garden",
      "address": "",
      "score": 8,
      "reason": "Major artist performance; significant entertainment event",
      "_proximity": 3
    },
    {
      "source": "do617:concerts",
      "name": "Lady Gaga",
      "description": "",
      "url": "https://do617.com/events/2026/3/30/lady-gaga-tickets",
      "start": "2026-03-30T20:00",
      "venue": "TD Garden",
      "address": "",
      "score": 8,
      "reason": "Major concert event; high-profile entertainment",
      "_proximity": 3
    },
    {
      "source": "do617:food-drink",
      "name": "Omakase\u2026The Baby\u2019s Way",
      "description": "",
      "url": "https://do617.com/events/2026/3/25/omakasethe-babys-way-tickets",
      "start": "2026-03-25T19:00",
      "venue": "Fat Baby",
      "address": "",
      "score": 7,
      "reason": "Omakase dining experience - high-end food event",
      "_proximity": 3
    },
    {
      "source": "do617:food-drink",
      "name": "Copy of Hands-On: Pasta alla Carbonara",
      "description": "",
      "url": "https://do617.com/events/2026/3/25/copy-of-hands-on-pasta-alla-carbonara-tickets",
      "start": "2026-03-25T15:00",
      "venue": "Eataly Boston",
      "address": "",
      "score": 7,
      "reason": "Hands-on pasta cooking class - upscale food experience",
      "_proximity": 3
    },
    {
      "source": "do617:food-drink",
      "name": "Hands-On: Pasta alla Puttanesca",
      "description": "",
      "url": "https://do617.com/events/2026/3/25/hands-on-pasta-alla-puttanesca-tickets",
      "start": "2026-03-25T18:00",
      "venue": "Eataly Boston",
      "address": "",
      "score": 7,
      "reason": "Hands-on Italian pasta cooking class",
      "_proximity": 3
    },
    {
      "source": "do617:food-drink",
      "name": "Hands-On: Pasta all'Amatriciana",
      "description": "",
      "url": "https://do617.com/events/2026/3/26/hands-on-pasta-all-amatriciana-tickets",
      "start": "2026-03-26T15:00",
      "venue": "Eataly Boston",
      "address": "",
      "score": 7,
      "reason": "Hands-on Italian pasta cooking class",
      "_proximity": 3
    },
    {
      "source": "do617:food-drink",
      "name": "Hands-On: Pasta alla Norcina al Tartufo",
      "description": "",
      "url": "https://do617.com/events/2026/3/26/hands-on-pasta-alla-norcina-al-tartufo-tickets",
      "start": "2026-03-26T18:00",
      "venue": "Eataly Boston",
      "address": "",
      "score": 7,
      "reason": "Hands-on Italian pasta cooking class with truffle",
      "_proximity": 3
    },
    {
      "source": "do617:food-drink",
      "name": "Mixology Class | Spring Cocktails",
      "description": "",
      "url": "https://do617.com/events/2026/3/28/mixology-class-spring-cocktails-tickets",
      "start": "2026-03-28T18:00",
      "venue": "Short Path Distillery",
      "address": "",
      "score": 7,
      "reason": "Mixology class for cocktails - upscale beverage education/experience",
      "_proximity": 3
    },
    {
      "source": "do617:food-drink",
      "name": "Class: Ramen Masterclass",
      "description": "",
      "url": "https://do617.com/events/2026/3/28/class-ramen-masterclass-tickets",
      "start": "2026-03-28T13:00",
      "venue": "Pagu",
      "address": "",
      "score": 7,
      "reason": "Ramen masterclass - elevated culinary education",
      "_proximity": 3
    },
    {
      "source": "do617:food-drink",
      "name": "Jazz Dinner w/ Jordan Gravel!",
      "description": "",
      "url": "https://do617.com/events/2026/3/30/jazz-dinner-w-jordan-gravel-tickets",
      "start": "2026-03-30T19:00",
      "venue": "Gulu-Gulu Cafe",
      "address": "",
      "score": 7,
      "reason": "Upscale dinner event with live jazz \u2014 fits high-status food/drink + entertainment profile",
      "_proximity": 3
    },
    {
      "source": "do617:food-drink",
      "name": "Cookbook Release Party",
      "description": "",
      "url": "https://do617.com/events/2026/3/31/cookbook-release-party-tickets",
      "start": "2026-03-31T18:00",
      "venue": "Citrus and Salt",
      "address": "",
      "score": 7,
      "reason": "Cookbook release party \u2014 upscale food/drink event, likely with interesting crowd and networking",
      "_proximity": 3
    },
    {
      "source": "do617:film-theatre-performing-arts",
      "name": "Colorful Cosmopolitanism: Artistic Representations of the Nation as Mother",
      "description": "",
      "url": "https://do617.com/events/2026/3/26/colorful-cosmopolitanism-artistic-representations-of-the-nation-as-mother-tickets",
      "start": "2026-03-26T14:00",
      "venue": "Museum of Fine Arts Boston",
      "address": "",
      "score": 7,
      "reason": "Colorful Cosmopolitanism - intellectual art/cultural panel on nation and artistic representation",
      "_proximity": 3
    },
    {
      "source": "do617:film-theatre-performing-arts",
      "name": "Teaching with Hindu Art: Depictions of the Divine in Prints, Paintings, and Sculptures",
      "description": "",
      "url": "https://do617.com/events/2026/3/26/teaching-with-hindu-art-depictions-of-the-divine-in-prints-paintings-and-sculptures-tickets",
      "start": "2026-03-26T16:30",
      "venue": "Museum of Fine Arts Boston",
      "address": "",
      "score": 7,
      "reason": "Teaching with Hindu Art - cultural art panel on divine representations, open to public",
      "_proximity": 3
    },
    {
      "source": "do617:film-theatre-performing-arts",
      "name": "Suffs",
      "description": "",
      "url": "https://do617.com/events/2026/3/27/suffs-tickets",
      "start": "2026-03-27T20:00",
      "venue": "Emerson Colonial Theatre",
      "address": "",
      "score": 7,
      "reason": "Suffs is a Tony-nominated Broadway musical about women's suffrage\u2014upscale theater event with historical/civic interest",
      "_proximity": 3
    },
    {
      "source": "do617:film-theatre-performing-arts",
      "name": "Suffs",
      "description": "",
      "url": "https://do617.com/events/2026/3/28/suffs-tickets-9ekyek6",
      "start": "2026-03-28T20:00",
      "venue": "Emerson Colonial Theatre",
      "address": "",
      "score": 7,
      "reason": "Suffs (duplicate)\u2014Tony-nominated Broadway musical with civic/historical themes",
      "_proximity": 3
    },
    {
      "source": "do617:film-theatre-performing-arts",
      "name": "Castle of Our Skins with Daniel Bernard Roumain, electric violin and Val-Inc, sound chemist",
      "description": "",
      "url": "https://do617.com/events/2026/3/29/castle-of-our-skins-with-daniel-bernard-roumain-electric-violin-and-val-inc-sound-chemist-tickets",
      "start": "2026-03-29T13:30",
      "venue": "Isabella Stewart Gardner Museum",
      "address": "",
      "score": 7,
      "reason": "Performance art event with accomplished musicians (Daniel Bernard Roumain)\u2014high-quality cultural experience",
      "_proximity": 3
    },
    {
      "source": "do617:film-theatre-performing-arts",
      "name": "Good Writing: An Evening with Anne Lamott & Neal Allen",
      "description": "",
      "url": "https://do617.com/events/2026/3/30/good-writing-an-evening-with-anne-lamott-neal-allen-tickets",
      "start": "2026-03-30T19:30",
      "venue": "Emerson Colonial Theatre",
      "address": "",
      "score": 7,
      "reason": "Literary event with established authors; intellectual and cultural appeal",
      "_proximity": 3
    },
    {
      "source": "do617:film-theatre-performing-arts",
      "name": "GRAYSCALE Indie Business Summit",
      "description": "",
      "url": "https://do617.com/events/2026/3/31/grayscale-indie-business-summit-tickets",
      "start": "2026-03-31T10:00",
      "venue": "CinemaSalem",
      "address": "",
      "score": 7,
      "reason": "GRAYSCALE Indie Business Summit \u2014 startup/business networking, professional development",
      "_proximity": 3
    },
    {
      "source": "do617:concerts",
      "name": "Lori Z Jazz Trio: Barside ft. Lori Zuroff on vocals, Molly Flannery on piano and Bill McCormack on bass.",
      "description": "",
      "url": "https://do617.com/events/2026/3/25/lori-z-jazz-trio-barside-ft-lori-zuroff-on-vocals-molly-flannery-on-piano-and-bill-mccormack-on-bass-tickets",
      "start": "2026-03-25T17:15",
      "venue": "Sanctuary - Cultural Arts Center",
      "address": "",
      "score": 7,
      "reason": "Upscale jazz trio at a bar venue; sophisticated live music experience",
      "_proximity": 3
    },
    {
      "source": "do617:concerts",
      "name": "Imagining Museums: The Next 150 Years of Stewarding Art at Wellesley",
      "description": "",
      "url": "https://do617.com/events/2026/3/26/imagining-museums-the-next-150-years-of-stewarding-art-at-wellesley-tickets",
      "start": "2026-03-26T09:00",
      "venue": "Lulu Chow Wang Campus Center",
      "address": "",
      "score": 7,
      "reason": "Museum symposium on cultural stewardship; intellectually substantive cultural forum",
      "_proximity": 3
    },
    {
      "source": "do617:concerts",
      "name": "Dvo\u0159\u00e1k Symphony No. 9 and Excerpts from Nixon in China with Ren\u00e9e Fleming",
      "description": "",
      "url": "https://do617.com/events/2026/3/27/dvorak-symphony-no-9-and-excerpts-from-nixon-in-china-with-renee-fleming-tickets-7075560",
      "start": "2026-03-27T19:30",
      "venue": "Symphony Hall, Boston, MA",
      "address": "",
      "score": 7,
      "reason": "Classical music performance featuring renowned soprano Ren\u00e9e Fleming at what appears to be a prestigious venue; upscale cultural event",
      "_proximity": 3
    },
    {
      "source": "do617:concerts",
      "name": "Dvo\u0159\u00e1k Symphony No. 9 and Excerpts from Nixon in China with Ren\u00e9e Fleming",
      "description": "",
      "url": "https://do617.com/events/2026/3/27/dvorak-symphony-no-9-and-excerpts-from-nixon-in-china-with-renee-fleming-tickets",
      "start": "2026-03-27T19:30",
      "venue": "Boston Symphony Hall",
      "address": "",
      "score": 7,
      "reason": "Classical music performance featuring renowned soprano Ren\u00e9e Fleming at what appears to be a prestigious venue; upscale cultural event",
      "_proximity": 3
    },
    {
      "source": "do617:concerts",
      "name": "Diana Krall",
      "description": "",
      "url": "https://do617.com/events/2026/3/28/diana-krall-tickets",
      "start": "2026-03-28T20:00",
      "venue": "The Cabot",
      "address": "",
      "score": 7,
      "reason": "Diana Krall is an internationally acclaimed jazz pianist; high-caliber upscale musical performance",
      "_proximity": 3
    },
    {
      "source": "do617:concerts",
      "name": "Dvo\u0159\u00e1k Symphony No. 9 and Excerpts from Nixon in China with Ren\u00e9e Fleming",
      "description": "",
      "url": "https://do617.com/events/2026/3/28/dvorak-symphony-no-9-and-excerpts-from-nixon-in-china-with-renee-fleming-tickets-xmybbq7",
      "start": "2026-03-28T20:00",
      "venue": "Symphony Hall, Boston, MA",
      "address": "",
      "score": 7,
      "reason": "Classical music with renowned performer Ren\u00e9e Fleming; upscale cultural event",
      "_proximity": 3
    },
    {
      "source": "do617:concerts",
      "name": "Emanuel Ax, piano",
      "description": "",
      "url": "https://do617.com/events/2026/3/29/emanuel-ax-piano-tickets",
      "start": "2026-03-29T15:00",
      "venue": "Shalin Liu Performance Center",
      "address": "",
      "score": 7,
      "reason": "Classical piano performance by acclaimed pianist Emanuel Ax; upscale cultural event",
      "_proximity": 3
    },
    {
      "source": "do617:concerts",
      "name": "Joel Kim Booster",
      "description": "",
      "url": "https://do617.com/events/2026/3/30/joel-kim-booster-tickets",
      "start": "2026-03-30T19:30",
      "venue": "Crystal Ballroom at Somerville Theatre",
      "address": "",
      "score": 7,
      "reason": "Comedy show by established performer; entertainment",
      "_proximity": 4
    },
    {
      "source": "do617:concerts",
      "name": "Gile Series: Ladysmith Black Mambazo",
      "description": "",
      "url": "https://do617.com/events/2026/3/31/ladysmith-black-mambazo-tickets",
      "start": "2026-03-31T19:00",
      "venue": "Capitol Center for the Arts",
      "address": "",
      "score": 7,
      "reason": "Gile Series concert; established world music act; cultural event",
      "_proximity": 3
    },
    {
      "source": "luma:boston",
      "name": "Resolution Hacks (w. Eight Sleep, swsh, Duckbill, Fragile, Clair & Wayfair)",
      "description": "",
      "url": "https://lu.ma/w8yvu0hq",
      "start": "2026-03-28T13:00",
      "venue": "",
      "address": "Cambridge, Massachusetts",
      "score": 7,
      "reason": "Multi-company startup/product hackathon with established brands \u2014 strong VC/startup networking",
      "_proximity": 5
    },
    {
      "source": "luma:boston",
      "name": "Boston Founders & IP Night",
      "description": "",
      "url": "https://lu.ma/3l7iyd13",
      "start": "2026-03-31T23:30",
      "venue": "",
      "address": "Cambridge, Massachusetts",
      "score": 7,
      "reason": "Founders + IP networking night \u2014 direct entrepreneurship/legal expertise intersection, high-value crowd",
      "_proximity": 5
    },
    {
      "source": "allevents:business",
      "name": "28th Africa Business Conference at Harvard Business School",
      "description": "",
      "url": "https://allevents.in/boston/28th-africa-business-conference-at-harvard-business-school/100001948942331979",
      "start": "2026-03-27",
      "venue": "Harvard Business School",
      "address": "Boston, MA",
      "score": 7,
      "reason": "Africa Business Conference at HBS \u2014 high-status professional forum, Harvard venue, policy/business networking",
      "_proximity": 3
    },
    {
      "source": "do617:film-theatre-performing-arts",
      "name": "T. Kingfisher: Wolf Worm",
      "description": "",
      "url": "https://do617.com/events/2026/3/25/t-kingfisher-wolf-worm-tickets",
      "start": "2026-03-25T18:00",
      "venue": "Brookline Booksmith",
      "address": "",
      "score": 6,
      "reason": "Author reading event\u2014upscale literary scene and intellectual networking",
      "_proximity": 5
    },
    {
      "source": "do617:film-theatre-performing-arts",
      "name": "Salem Film Fest",
      "description": "",
      "url": "https://do617.com/events/2026/3/28/salem-film-fest-tickets",
      "start": "2026-03-28T10:00",
      "venue": "Downtown Salem",
      "address": "",
      "score": 6,
      "reason": "Film festival\u2014cultural event open to public, potential for upscale social scene",
      "_proximity": 8
    },
    {
      "source": "allevents:business",
      "name": "Latino Professional Mixer 2026",
      "description": "",
      "url": "https://allevents.in/boston/latino-professional-mixer-2026/100001981877024531",
      "start": "2026-03-26",
      "venue": "Courtyard by Marriott Boston Downtown",
      "address": "Boston, MA",
      "score": 6,
      "reason": "Professional networking mixer \u2014 good crowd, Brian values diverse professional events",
      "_proximity": 8
    }
  ],
  "extra_events": [
    {
      "name": "Mayflower Brewing's Spring Warehouse Jam Series: The Dirty Water Dance Band",
      "score": 4,
      "reason": "Brewery event with live music is casual/fun but lacks the upscale food/drink, networking, or high-status elements this user seeks. Not exclusive or scene-y enough to warrant attendance.",
      "url": "https://do617.com/events/2026/3/27/mayflower-brewing-s-spring-warehouse-jam-series-the-dirty-water-dance-band-tickets"
    }
  ],
  "oyster_deals": [
    {
      "source": "deep_research",
      "name": "Lower Mills Tavern \u2014 $1 oysters",
      "description": "Dorchester. $1 oysters, Mondays, 4:00 PM until sold out.",
      "url": "",
      "start": "",
      "venue": "Lower Mills Tavern",
      "address": "Dorchester",
      "score": 10,
      "reason": "Dollar oysters, Mondays, sold out basis indicates popularity"
    },
    {
      "source": "deep_research",
      "name": "224 Boston \u2014 $1 oysters",
      "description": "Dorchester. $1 oysters, Mondays & Tuesdays, 5:00 PM - 10:00 PM.",
      "url": "",
      "start": "",
      "venue": "224 Boston",
      "address": "Dorchester",
      "score": 10,
      "reason": "Dollar oysters, two days per week, extended evening hours"
    },
    {
      "source": "deep_research",
      "name": "Batifol \u2014 $1 oysters",
      "description": "Kendall Square. $1 oysters, Daily, 4:00 PM - 6:00 PM.",
      "url": "",
      "start": "",
      "venue": "Batifol",
      "address": "Kendall Square",
      "score": 10,
      "reason": "Dollar oysters daily, 2-hour happy hour window"
    },
    {
      "source": "deep_research",
      "name": "Bambara Kitchen \u2014 $1 oysters",
      "description": "East Cambridge. $1 oysters, Daily, 5:00 PM - 7:00 PM.",
      "url": "",
      "start": "",
      "venue": "Bambara Kitchen",
      "address": "East Cambridge",
      "score": 10,
      "reason": "Dollar oysters daily, 2-hour evening happy hour"
    },
    {
      "source": "deep_research",
      "name": "Viale \u2014 $1 oysters",
      "description": "Central Square. $1 oysters, Sat-Thu 5:00-7:00 PM; Fridays 4:00-7:00 PM.",
      "url": "",
      "start": "",
      "venue": "Viale",
      "address": "Central Square",
      "score": 10,
      "reason": "Dollar oysters daily with extended Friday hours"
    },
    {
      "source": "deep_research",
      "name": "Althea \u2014 $1 oysters",
      "description": "Central Square. $1 oysters, Daily, 2:00 PM - 5:00 PM.",
      "url": "",
      "start": "",
      "venue": "Althea",
      "address": "Central Square",
      "score": 10,
      "reason": "Dollar oysters daily, 3-hour afternoon window"
    },
    {
      "source": "deep_research",
      "name": "Russell House Tavern \u2014 $1 oysters",
      "description": "Harvard Square. $1 oysters, Sun-Thu 9:00-11:00 PM; Fri-Sat 10:00 PM-12:00 AM.",
      "url": "",
      "start": "",
      "venue": "Russell House Tavern",
      "address": "Harvard Square",
      "score": 10,
      "reason": "Dollar oysters nightly, late-night happy hour option"
    },
    {
      "source": "deep_research",
      "name": "Grafton Street Pub \u2014 $1 oysters",
      "description": "Harvard Square. $1 oysters, Monday \u2013 Friday, 5:00 PM - 7:00 PM.",
      "url": "",
      "start": "",
      "venue": "Grafton Street Pub",
      "address": "Harvard Square",
      "score": 10,
      "reason": "Dollar oysters weekdays, prime happy hour time"
    },
    {
      "source": "deep_research",
      "name": "Charlie's Kitchen \u2014 $1 oysters ($2 normally)",
      "description": "Harvard Square. $1 oysters ($2 normally), Sundays, 12:00 PM - 4:00 PM & 6:00-8:00 PM.",
      "url": "",
      "start": "",
      "venue": "Charlie's Kitchen",
      "address": "Harvard Square",
      "score": 10,
      "reason": "Dollar oysters Sundays, two time windows, 50% discount from $2"
    },
    {
      "source": "deep_research",
      "name": "Caf\u00e9 Saint-Germain \u2014 $1 oysters",
      "description": "Cambridge. $1 oysters, Daily, 4:00 PM - 6:00 PM.",
      "url": "",
      "start": "",
      "venue": "Caf\u00e9 Saint-Germain",
      "address": "Cambridge",
      "score": 10,
      "reason": "Dollar oysters daily, 2-hour afternoon window"
    },
    {
      "source": "deep_research",
      "name": "Vera's \u2014 $1 oysters",
      "description": "Union Square. $1 oysters, Tuesday \u2013 Sunday, 5:00 PM - 6:00 PM.",
      "url": "",
      "start": "",
      "venue": "Vera's",
      "address": "Union Square",
      "score": 10,
      "reason": "Dollar oysters 5+ days per week, 1-hour evening window"
    },
    {
      "source": "deep_research",
      "name": "La Brasa \u2014 $1 oysters",
      "description": "East Somerville. $1 oysters, Daily, 5:00 PM - 6:00 PM.",
      "url": "",
      "start": "",
      "venue": "La Brasa",
      "address": "East Somerville",
      "score": 10,
      "reason": "Dollar oysters daily, 1-hour evening happy hour"
    },
    {
      "source": "deep_research",
      "name": "Legal Sea Foods \u2014 $1 oysters",
      "description": "Chestnut Hill (Brookline border). $1 oysters, Daily, 3:00 PM - 6:00 PM (Dine-in bar area only).",
      "url": "",
      "start": "",
      "venue": "Legal Sea Foods",
      "address": "Chestnut Hill (Brookline border)",
      "score": 10,
      "reason": "Dollar oysters daily, 3-hour window, established chain venue"
    },
    {
      "source": "known_venue",
      "name": "Island Creek Oyster Bar \u2014 $1 oysters at the bar, select hours",
      "description": "Kenmore. Standing deal: $1 oysters at the bar, select hours",
      "url": "https://islandcreekoysters.com/pages/boston",
      "start": "",
      "venue": "Island Creek Oyster Bar",
      "address": "Kenmore",
      "score": 9,
      "reason": "Dollar oysters at the bar at upscale Island Creek Oyster Bar"
    },
    {
      "source": "known_venue",
      "name": "Row 34 \u2014 Dollar oysters Mon\u2013Wed 5\u20136pm",
      "description": "Fort Point. Standing deal: Dollar oysters Mon\u2013Wed 5\u20136pm",
      "url": "https://www.row34.com",
      "start": "",
      "venue": "Row 34",
      "address": "Fort Point",
      "score": 9,
      "reason": "Dollar oysters Mon\u2013Wed 5\u20136pm at respected Fort Point seafood spot"
    },
    {
      "source": "known_venue",
      "name": "Woods Hill Pier 4 \u2014 Dollar oysters Mon\u2013Wed 5\u20136pm",
      "description": "Seaport. Standing deal: Dollar oysters Mon\u2013Wed 5\u20136pm",
      "url": "https://www.woodshillpier4.com",
      "start": "",
      "venue": "Woods Hill Pier 4",
      "address": "Seaport",
      "score": 9,
      "reason": "Dollar oysters Mon\u2013Wed 5\u20136pm at upscale Woods Hill Pier 4"
    },
    {
      "source": "deep_research",
      "name": "Rochambeau \u2014 $1 oysters",
      "description": "Back Bay. $1 oysters, Daily, 3:00 PM - 6:00 PM.",
      "url": "",
      "start": "",
      "venue": "Rochambeau",
      "address": "Back Bay",
      "score": 9,
      "reason": "Dollar oysters daily 3\u20136pm at Back Bay's Rochambeau"
    },
    {
      "source": "deep_research",
      "name": "Citizen Public House \u2014 $1 oysters",
      "description": "Fenway. $1 oysters, Monday \u2013 Saturday, 4:00 PM - 2:00 AM.",
      "url": "",
      "start": "",
      "venue": "Citizen Public House",
      "address": "Fenway",
      "score": 9,
      "reason": "Dollar oysters Mon\u2013Sat 4pm\u20132am at Citizen Public House Fenway"
    },
    {
      "source": "deep_research",
      "name": "Trillium Brewing Co. \u2014 $1 oysters",
      "description": "Fort Point. $1 oysters, Monday \u2013 Friday, 2:00 PM - 4:00 PM.",
      "url": "",
      "start": "",
      "venue": "Trillium Brewing Co.",
      "address": "Fort Point",
      "score": 9,
      "reason": "Dollar oysters, weekday afternoon happy hour, 2-hour window"
    },
    {
      "source": "deep_research",
      "name": "The Independent \u2014 $1 oysters",
      "description": "Union Square. $1 oysters, Mondays, 4:00 PM - 10:00 PM.",
      "url": "",
      "start": "",
      "venue": "The Independent",
      "address": "Union Square",
      "score": 9,
      "reason": "Dollar oysters Mondays, extended 6-hour window"
    },
    {
      "source": "deep_research",
      "name": "Thirsty Scholar Pub \u2014 $1 oysters",
      "description": "Somerville (Teele Sq area). $1 oysters, Tuesdays, 4:00 PM until sold out.",
      "url": "",
      "start": "",
      "venue": "Thirsty Scholar Pub",
      "address": "Somerville (Teele Sq area)",
      "score": 9,
      "reason": "Dollar oysters Tuesdays, sold out basis indicates value"
    },
    {
      "source": "known_venue",
      "name": "Russell House Tavern \u2014 $1 oysters 9\u201310pm Sun & Mon",
      "description": "Harvard Square. Standing deal: $1 oysters 9\u201310pm Sun & Mon",
      "url": "https://www.russellhouserestaurant.com",
      "start": "",
      "venue": "Russell House Tavern",
      "address": "Harvard Square",
      "score": 8,
      "reason": "Dollar oysters 9\u201310pm Sun & Mon at Harvard Square tavern"
    },
    {
      "source": "known_venue",
      "name": "Legal Sea Foods Long Wharf \u2014 $1 oysters daily 3-6pm (bar area only)",
      "description": "Downtown/Waterfront. Standing deal: $1 oysters daily 3-6pm (bar area only)",
      "url": "https://www.legalseafoods.com/restaurants/boston-long-wharf",
      "start": "",
      "venue": "Legal Sea Foods Long Wharf",
      "address": "Downtown/Waterfront",
      "score": 8,
      "reason": "Dollar oysters daily 3\u20136pm at Legal Sea Foods Long Wharf"
    },
    {
      "source": "known_venue",
      "name": "Legal Sea Foods Prudential \u2014 $1 oysters daily 3-6pm (bar area only)",
      "description": "Back Bay. Standing deal: $1 oysters daily 3-6pm (bar area only)",
      "url": "https://www.legalseafoods.com/restaurants/boston-prudential-center",
      "start": "",
      "venue": "Legal Sea Foods Prudential",
      "address": "Back Bay",
      "score": 8,
      "reason": "Dollar oysters daily 3\u20136pm at Legal Sea Foods Prudential"
    },
    {
      "source": "deep_research",
      "name": "Fin Point Oyster Bar + Grille \u2014 $1 oysters",
      "description": "Financial District. $1 oysters, Thursday \u2013 Sunday, 2:00 PM - 5:00 PM.",
      "url": "",
      "start": "",
      "venue": "Fin Point Oyster Bar + Grille",
      "address": "Financial District",
      "score": 8,
      "reason": "Dollar oysters Thu\u2013Sun 2\u20135pm at Fin Point Oyster Bar"
    },
    {
      "source": "deep_research",
      "name": "State Street Provisions \u2014 $1 oysters",
      "description": "Downtown/Waterfront. $1 oysters, Monday \u2013 Friday, 3:00 PM - 5:00 PM.",
      "url": "",
      "start": "",
      "venue": "State Street Provisions",
      "address": "Downtown/Waterfront",
      "score": 8,
      "reason": "Dollar oysters Mon\u2013Fri 3\u20135pm at State Street Provisions"
    },
    {
      "source": "deep_research",
      "name": "The Merchant \u2014 $1 oysters",
      "description": "Downtown. $1 oysters, Monday & Friday, 4:00 PM - 7:00 PM.",
      "url": "",
      "start": "",
      "venue": "The Merchant",
      "address": "Downtown",
      "score": 8,
      "reason": "Dollar oysters Mon & Fri 4\u20137pm at The Merchant"
    },
    {
      "source": "deep_research",
      "name": "The Bosworth \u2014 $1 oysters",
      "description": "Downtown. $1 oysters, Daily, starting at 5:00 PM (while supplies last).",
      "url": "",
      "start": "",
      "venue": "The Bosworth",
      "address": "Downtown",
      "score": 8,
      "reason": "Dollar oysters daily from 5pm at The Bosworth"
    },
    {
      "source": "deep_research",
      "name": "Joe's Waterfront \u2014 $1 oysters",
      "description": "Downtown/Waterfront. $1 oysters, Daily, 5:00 PM to close (Seasonal through March).",
      "url": "",
      "start": "",
      "venue": "Joe's Waterfront",
      "address": "Downtown/Waterfront",
      "score": 8,
      "reason": "Dollar oysters daily 5pm\u2013close (seasonal) at Joe's Waterfront"
    },
    {
      "source": "deep_research",
      "name": "Bostonia Public House \u2014 $1 oysters",
      "description": "Financial District. $1 oysters, Monday \u2013 Friday, 3:00 PM - 6:00 PM.",
      "url": "",
      "start": "",
      "venue": "Bostonia Public House",
      "address": "Financial District",
      "score": 8,
      "reason": "Dollar oysters Mon\u2013Fri 3\u20136pm at Bostonia Public House"
    },
    {
      "source": "deep_research",
      "name": "Carrie Nation Cocktail Club \u2014 $1 oysters",
      "description": "Beacon Hill. $1 oysters, Tuesday \u2013 Thursday, 4:00 PM - 7:00 PM.",
      "url": "",
      "start": "",
      "venue": "Carrie Nation Cocktail Club",
      "address": "Beacon Hill",
      "score": 8,
      "reason": "Dollar oysters Tue\u2013Thu 4\u20137pm at Carrie Nation Cocktail Club"
    },
    {
      "source": "deep_research",
      "name": "Bootleg Special \u2014 $1 oysters",
      "description": "Back Bay. $1 oysters, Thursdays 5:00-10:00 PM; Fri-Sat late-night 10:00 PM.",
      "url": "",
      "start": "",
      "venue": "Bootleg Special",
      "address": "Back Bay",
      "score": 8,
      "reason": "Dollar oysters Thu 5\u201310pm and Fri\u2013Sat late-night at Bootleg Special"
    },
    {
      "source": "deep_research",
      "name": "Sonsie \u2014 $1 oysters",
      "description": "Back Bay. $1 oysters, Wednesday \u2013 Sunday, 3:00 PM - 4:00 PM.",
      "url": "",
      "start": "",
      "venue": "Sonsie",
      "address": "Back Bay",
      "score": 8,
      "reason": "Dollar oysters Wed\u2013Sun 3\u20134pm at Sonsie"
    },
    {
      "source": "deep_research",
      "name": "Limani \u2014 $1 oysters",
      "description": "Seaport. $1 oysters, Monday \u2013 Friday, 4:00 PM - 6:00 PM.",
      "url": "",
      "start": "",
      "venue": "Limani",
      "address": "Seaport",
      "score": 8,
      "reason": "Dollar oysters Mon\u2013Fri 4\u20136pm at Limani Seaport"
    },
    {
      "source": "deep_research",
      "name": "Matria \u2014 $1 oysters",
      "description": "Seaport. $1 oysters, Thursdays, 4:00 PM - 7:00 PM.",
      "url": "",
      "start": "",
      "venue": "Matria",
      "address": "Seaport",
      "score": 8,
      "reason": "Dollar oysters Thu 4\u20137pm at Matria Seaport"
    },
    {
      "source": "deep_research",
      "name": "Lincoln Tavern & Restaurant \u2014 $1 oysters & $1 shrimp",
      "description": "South Boston. $1 oysters & $1 shrimp, Tuesdays, 10:00 AM - 10:00 PM (Summer Fri 1-4 PM).",
      "url": "",
      "start": "",
      "venue": "Lincoln Tavern & Restaurant",
      "address": "South Boston",
      "score": 8,
      "reason": "Dollar oysters Tue 10am\u201310pm (summer Fri 1\u20134pm) at Lincoln Tavern"
    },
    {
      "source": "deep_research",
      "name": "Loco Taqueria & Oyster Bar \u2014 $1 oysters",
      "description": "South Boston. $1 oysters, Mondays, 11:00 AM - 12:30 AM.",
      "url": "",
      "start": "",
      "venue": "Loco Taqueria & Oyster Bar",
      "address": "South Boston",
      "score": 8,
      "reason": "Dollar oysters all-day Monday at Loco Taqueria & Oyster Bar"
    },
    {
      "source": "deep_research",
      "name": "The Broadway \u2014 $1 oysters",
      "description": "South Boston. $1 oysters, Wednesdays 11:30 AM - 1:00 AM; Daily 2:00 PM - 6:00 PM.",
      "url": "",
      "start": "",
      "venue": "The Broadway",
      "address": "South Boston",
      "score": 8,
      "reason": "Dollar oysters Wed 11:30am\u20131am and daily 2\u20136pm at The Broadway"
    },
    {
      "source": "deep_research",
      "name": "Publico Street Bistro & Garden \u2014 $1 oysters & shrimp",
      "description": "South Boston. $1 oysters & shrimp, Mondays & Tuesdays, 11:00 AM to close (or until sold out); Thursdays.",
      "url": "",
      "start": "",
      "venue": "Publico Street Bistro & Garden",
      "address": "South Boston",
      "score": 8,
      "reason": "Dollar oysters & shrimp Mon\u2013Tue and Thu at Publico Street Bistro"
    },
    {
      "source": "deep_research",
      "name": "Ilona \u2014 $1 oysters",
      "description": "South End. $1 oysters, Thursdays 5:00 PM - 1:00 AM; Fri-Sat 4:00 PM - 7:00 PM.",
      "url": "",
      "start": "",
      "venue": "Ilona",
      "address": "South End",
      "score": 8,
      "reason": "Dollar oysters Thu 5pm\u20131am and Fri\u2013Sat 4\u20137pm at Ilona"
    },
    {
      "source": "deep_research",
      "name": "Petit Robert Bistro \u2014 $1 oysters (limit 16 pp)",
      "description": "South End. $1 oysters (limit 16 pp), Monday \u2013 Thursday, 3:00 PM - 6:00 PM.",
      "url": "",
      "start": "",
      "venue": "Petit Robert Bistro",
      "address": "South End",
      "score": 8,
      "reason": "Dollar oysters (limit 16pp) Mon\u2013Thu 3\u20136pm at Petit Robert Bistro"
    },
    {
      "source": "deep_research",
      "name": "Yellow Door Taqueria \u2014 $1 oysters",
      "description": "South End / Dorchester. $1 oysters, Sundays, 12:00 PM until sold out (\"Shuck It Sundays\").",
      "url": "",
      "start": "",
      "venue": "Yellow Door Taqueria",
      "address": "South End / Dorchester",
      "score": 8,
      "reason": "Dollar oysters Sundays until sold out at Yellow Door Taqueria"
    },
    {
      "source": "deep_research",
      "name": "Rail Stop \u2014 $1 oysters",
      "description": "Brighton. $1 oysters, Monday \u2013 Friday, 3:00 PM - 6:00 PM.",
      "url": "",
      "start": "",
      "venue": "Rail Stop",
      "address": "Brighton",
      "score": 8,
      "reason": "Dollar oysters Mon\u2013Fri 3\u20136pm at Rail Stop Brighton"
    },
    {
      "source": "deep_research",
      "name": "Warren Tavern \u2014 $1 oysters",
      "description": "Charlestown. $1 oysters, Monday \u2013 Friday, 3:00 PM - 6:00 PM.",
      "url": "",
      "start": "",
      "venue": "Warren Tavern",
      "address": "Charlestown",
      "score": 8,
      "reason": "Dollar oysters Mon\u2013Fri 3\u20136pm at Warren Tavern Charlestown"
    },
    {
      "source": "deep_research",
      "name": "Tradesman \u2014 $1 Duxbury oysters",
      "description": "Charlestown. $1 Duxbury oysters, Saturday & Sunday, 11:00 AM - 3:00 PM.",
      "url": "",
      "start": "",
      "venue": "Tradesman",
      "address": "Charlestown",
      "score": 8,
      "reason": "Dollar Duxbury oysters Sat\u2013Sun 11am\u20133pm at Tradesman"
    },
    {
      "source": "deep_research",
      "name": "Monument Restaurant \u2014 $1 oysters",
      "description": "Charlestown. $1 oysters, Mondays, 11:30 AM - 11:00 PM.",
      "url": "",
      "start": "",
      "venue": "Monument Restaurant",
      "address": "Charlestown",
      "score": 8,
      "reason": "Dollar oysters all-day Monday at Monument Restaurant"
    },
    {
      "source": "deep_research",
      "name": "Savin Bar and Kitchen \u2014 $1 oysters (Call to confirm)",
      "description": "Dorchester. $1 oysters (Call to confirm), Monday \u2013 Friday, 4:00 PM - 6:00 PM.",
      "url": "",
      "start": "",
      "venue": "Savin Bar and Kitchen",
      "address": "Dorchester",
      "score": 8,
      "reason": "Dollar oysters Mon\u2013Fri 4\u20136pm at Savin Bar and Kitchen"
    },
    {
      "source": "deep_research",
      "name": "Waypoint \u2014 $2 oysters (Discounted)",
      "description": "Harvard/Central. $2 oysters (Discounted), Tuesday \u2013 Saturday, 5:00 PM to close.",
      "url": "",
      "start": "",
      "venue": "Waypoint",
      "address": "Harvard/Central",
      "score": 8,
      "reason": "Discounted $2 oysters, 5+ days per week, evening deal"
    },
    {
      "source": "deep_research",
      "name": "Punch Bowl \u2014 $1.25 oysters",
      "description": "Brookline Village. $1.25 oysters, Daily, 3:00 PM - 5:00 PM.",
      "url": "",
      "start": "",
      "venue": "Punch Bowl",
      "address": "Brookline Village",
      "score": 8,
      "reason": "Near-dollar oysters ($1.25) daily, 2-hour afternoon window"
    },
    {
      "source": "deep_research",
      "name": "Alcove \u2014 $1 oysters (with beverage purchase)",
      "description": "West End. $1 oysters (with beverage purchase), Monday \u2013 Friday, 3:00 PM - 5:00 PM.",
      "url": "",
      "start": "",
      "venue": "Alcove",
      "address": "West End",
      "score": 7,
      "reason": "Dollar oysters (with beverage purchase) Mon\u2013Fri 3\u20135pm at Alcove"
    },
    {
      "source": "deep_research",
      "name": "Rebel's Guild \u2014 $1 oysters (Bar only)",
      "description": "Back Bay. $1 oysters (Bar only), Tuesdays, 5:00 PM until sold out.",
      "url": "",
      "start": "",
      "venue": "Rebel's Guild",
      "address": "Back Bay",
      "score": 7,
      "reason": "Dollar oysters at bar Tuesdays until sold out at Rebel's Guild"
    },
    {
      "source": "deep_research",
      "name": "Woods Hill Pier \u2014 $1 oysters (Bar only, limit 1 dozen)",
      "description": "Seaport. $1 oysters (Bar only, limit 1 dozen), Sunday & Monday, 5:00 PM - 10:00 PM.",
      "url": "",
      "start": "",
      "venue": "Woods Hill Pier",
      "address": "Seaport",
      "score": 7,
      "reason": "Dollar oysters (bar only, limit 1 dozen) Sun & Mon 5\u201310pm at Woods Hill Pier"
    },
    {
      "source": "deep_research",
      "name": "Gray's Hall \u2014 $1 oysters",
      "description": "South Boston. $1 oysters, Tuesdays, open until sold out.",
      "url": "",
      "start": "",
      "venue": "Gray's Hall",
      "address": "South Boston",
      "score": 7,
      "reason": "Dollar oysters Tuesdays until sold out at Gray's Hall"
    },
    {
      "source": "deep_research",
      "name": "Prezza \u2014 $1 oysters (with beverage or app purchase)",
      "description": "North End. $1 oysters (with beverage or app purchase), Daily, 4:00 PM - 5:00 PM.",
      "url": "",
      "start": "",
      "venue": "Prezza",
      "address": "North End",
      "score": 7,
      "reason": "Dollar oysters (with beverage or app) daily 4\u20135pm at Prezza"
    },
    {
      "source": "deep_research",
      "name": "Summer Shack \u2014 $2 oysters (Discounted)",
      "description": "Cambridge (Alewife). $2 oysters (Discounted), Daily, all day.",
      "url": "",
      "start": "",
      "venue": "Summer Shack",
      "address": "Cambridge (Alewife)",
      "score": 7,
      "reason": "Discounted $2 oysters all day, daily availability"
    }
  ],
  "costs": {
    "week": 0.5762,
    "month": 0.7029,
    "total": 0.7029,
    "runs": [
      {
        "ts": "2026-03-25T15:16:36.915587",
        "events_total": 507,
        "events_cached": 109,
        "events_scored": 0,
        "cost_usd": 0.024414,
        "duration_ms": 24154,
        "models": {
          "claude-haiku-4-5-20251001": 0.024414
        }
      },
      {
        "ts": "2026-03-25T15:17:08.232722",
        "events_total": 507,
        "events_cached": 68,
        "events_scored": 288,
        "cost_usd": 0.050847,
        "duration_ms": 51188,
        "models": {
          "claude-haiku-4-5-20251001": 0.050847
        }
      },
      {
        "ts": "2026-03-25T17:06:07.117205",
        "events_total": 512,
        "events_cached": 109,
        "events_scored": 0,
        "cost_usd": 0.026933,
        "duration_ms": 25707,
        "models": {
          "claude-haiku-4-5-20251001": 0.026933
        }
      },
      {
        "ts": "2026-03-25T17:06:47.274212",
        "events_total": 512,
        "events_cached": 109,
        "events_scored": 0,
        "cost_usd": 0.026933,
        "duration_ms": 24584,
        "models": {
          "claude-haiku-4-5-20251001": 0.026933
        }
      },
      {
        "ts": "2026-03-25T17:22:39.909295",
        "events_total": 512,
        "events_cached": 109,
        "events_scored": 0,
        "cost_usd": 0.026933,
        "duration_ms": 24753,
        "models": {
          "claude-haiku-4-5-20251001": 0.026933
        }
      }
    ],
    "netlify": "1000/1000 credits remaining"
  },
  "sources": {
    "do617": 36,
    "luma": 2,
    "allevents": 2
  }
}